tests/__init__.py
tests/test_factories.py
tests/test_utils.py
tests/test_validators.py
tests/clients/__init__.py
tests/clients/test_base_client.py
tests/clients/test_bitfinex_client.py
tests/clients/test_kraken_client.py
tests/clients/test_okex_client.py
tests/fixtures/__init__.py
tests/fixtures/bitfinex.py
tests/fixtures/okex.py
tests/models/__init__.py
tests/models/test_base_models.py
tests/models/test_utils.py
xchange/__init__.py
xchange/exceptions.py
xchange/factories.py
xchange/utils.py
xchange/validators.py
xchange/clients/__init__.py
xchange/clients/base.py
xchange/clients/bitfinex.py
xchange/clients/kraken.py
xchange/clients/okex.py
xchange/constants/__init__.py
xchange/constants/currencies.py
xchange/constants/exchanges.py
xchange/models/__init__.py
xchange/models/base.py
xchange/models/bitfinex.py
xchange/models/kraken.py
xchange/models/okex.py
xchange/models/utils.py
xchange-0.0.6.dist-info/LICENSE
xchange-0.0.6.dist-info/METADATA
xchange-0.0.6.dist-info/WHEEL
xchange-0.0.6.dist-info/top_level.txt
xchange-0.0.6.dist-info/RECORD
