Metadata-Version: 2.1
Name: xchange
Version: 0.0.6
Summary: Many cryptocurrency exchange APIs, a single and unified API client
Home-page: https://github.com/martinzugnoni/xchange
Author: Martin Zugnoni
Author-email: martin.zugnoni@gmail.com
Maintainer: Martin Zugnoni
License: MIT
Download-URL: https://github.com/martinzugnoni/xchange/tarball/0.0.6
Platform: UNKNOWN
Classifier: Programming Language :: Python :: 3
Classifier: License :: OSI Approved :: MIT License
Classifier: Operating System :: OS Independent
Requires-Dist: requests (==2.18.4)
Requires-Dist: cached-property (==1.4.2)
